probabilistic_library/__init__.py
probabilistic_library/interface.py
probabilistic_library/logging.py
probabilistic_library/project.py
probabilistic_library/reliability.py
probabilistic_library/sensitivity.py
probabilistic_library/statistic.py
probabilistic_library/uncertainty.py
probabilistic_library/utils.py
probabilistic_library/bin/Deltares.Probabilistic.CWrapper.dll
probabilistic_library/bin/__init__.py
probabilistic_library/bin/libDeltares.Probabilistic.CWrapper.so
probabilistic_library-26.1.1rc3.dist-info/METADATA
probabilistic_library-26.1.1rc3.dist-info/WHEEL
probabilistic_library-26.1.1rc3.dist-info/top_level.txt
probabilistic_library-26.1.1rc3.dist-info/RECORD
