Metadata-Version: 2.4
Name: probabilistic_library
Version: 26.1.1rc3
Summary: Package which provides probabilistic methods
Author: Deltares
Author-email: Deltares <software.support@deltares.nl>
License: LGPL-3.0
Project-URL: Homepage, https://www.deltares.nl/software-en-data/producten/probabilistic-toolkit-ptk
Project-URL: Documentation, https://github.com/Deltares/ProbabilisticLibrary/tree/master/doc
Project-URL: Repository, https://github.com/Deltares/ProbabilisticLibrary
Project-URL: issues, https://github.com/Deltares/ProbabilisticLibrary/issues
Classifier: Operating System :: OS Independent
Classifier: Programming Language :: Python :: 3
Requires-Python: >=3.10
Requires-Dist: numpy
Requires-Dist: matplotlib
Dynamic: author
Dynamic: requires-python
